flit_pytest_circleci_template/__init__.py
flit_pytest_circleci_template-0.2.dist-info/WHEEL
flit_pytest_circleci_template-0.2.dist-info/METADATA
flit_pytest_circleci_template-0.2.dist-info/RECORD
